impetuous/__init__.py
impetuous/__main__.py
impetuous/config.py
impetuous/data.py
impetuous/epigraphs.yaml
impetuous/im.py
impetuous/interaction.py
impetuous/legacy.py
impetuous/serialization.py
impetuous/sheet.py
impetuous/simple_smile
impetuous/cli/__init__.py
impetuous/cli/actions.py
impetuous/cli/display.py
impetuous/ext/__init__.py
impetuous/ext/freshdesk.py
impetuous/ext/jira.py
impetuous/migrations/env.py
impetuous/migrations/versions/6fea50bb8562_actually_do_overlap_entry_detection.py
impetuous/migrations/versions/ea11786324dd_.py
impetuous/migrations/versions/f4aaf1bdf8c0_.py
impetuous/sql/check_insert_entry_dtrange.sql
impetuous/sql/check_update_entry_dtrange.sql
impetuous-1.0.9.dist-info/METADATA
impetuous-1.0.9.dist-info/WHEEL
impetuous-1.0.9.dist-info/entry_points.txt
impetuous-1.0.9.dist-info/top_level.txt
impetuous-1.0.9.dist-info/RECORD
