Metadata-Version: 2.1
Name: impetuous
Version: 1.0.9
Summary: CLI time tracking software indented for use with JIRA
Home-page: https://gitlab.com/sqwishy/impetuous
Author: sqwishy
Author-email: somebody@froghat.ca
License: GPLv3
Keywords: time tracking
Platform: UNKNOWN
Classifier: Development Status :: 3 - Alpha
Classifier: Intended Audience :: Developers
Classifier: Topic :: Office/Business
Classifier: Topic :: Utilities
Classifier: License :: OSI Approved :: GNU General Public License v3 (GPLv3)
Classifier: Programming Language :: Python :: 3.6
Requires-Dist: colorama (>=0.4.0)
Requires-Dist: python-dateutil (>=2.6.0)
Requires-Dist: pyyaml (>=3<4)
Requires-Dist: pytz (>=2018.9)
Requires-Dist: attrs (>=19.0.0)
Requires-Dist: sqlalchemy (>=1.2.0)
Requires-Dist: alembic (>=1.0.0)
Requires-Dist: aiohttp (>=3.0.0)
Provides-Extra: test
Requires-Dist: pytest ; extra == 'test'
Requires-Dist: pytest-benchmark ; extra == 'test'
Requires-Dist: pytest-asyncio ; extra == 'test'
